cheesegrader/__init__.py
cheesegrader/__main__.py
cheesegrader/api_tools/__init__.py
cheesegrader/api_tools/assignments.py
cheesegrader/api_tools/courses.py
cheesegrader/api_tools/tokens.py
cheesegrader/cli/__init__.py
cheesegrader/cli/copying.py
cheesegrader/cli/deleting.py
cheesegrader/cli/downloading.py
cheesegrader/cli/main.py
cheesegrader/cli/renaming.py
cheesegrader/cli/sorting.py
cheesegrader/cli/token.py
cheesegrader/cli/uploading.py
cheesegrader/cli/utils.py
cheesegrader/utils/__init__.py
cheesegrader/utils/file_utils.py
cheesegrader-1.3.7.dist-info/licenses/LICENSE
cheesegrader-1.3.7.dist-info/WHEEL
cheesegrader-1.3.7.dist-info/entry_points.txt
cheesegrader-1.3.7.dist-info/METADATA
cheesegrader-1.3.7.dist-info/RECORD
