Metadata-Version: 2.4
Name: cheesegrader
Version: 1.3.7
Summary: A collection of grading/quercus tools for University of Toronto instructors.
Author: Jesse Ward-Bond
Author-email: Jesse Ward-Bond <jesse.wardbond@mail.utoronto.ca>
License-Expression: GPL-3.0-or-later
License-File: LICENSE
Requires-Dist: requests>=2.32.5
Requires-Dist: tqdm>=4.67.1
Requires-Dist: typer>=0.20.0
Requires-Python: >=3.10
Project-URL: Homepage, https://github.com/jwardbond/cheesegrader
Project-URL: Issues, https://github.com/jwardbond/cheesegrader/issues
